[
  {
    "id": 37,
    "name": "Hydrus profmes.link Source Exports",
    "sources": [
      {
        "id": 94,
        "offline": false,
        "marked": false,
        "lastCheck": null,
        "tags": [],
        "clips": [],
        "disabledClips": [],
        "blacklist": [],
        "count": 0,
        "countComplete": false,
        "dirOfSources": false,
        "includeRetweets": false,
        "includeReplies": false,
        "url": "http://profmes.link:45869/get_files/search_files?tags=[\"ahego\", \"-exu\"]",
        "duration": null,
        "resolution": null
      },
      {
        "id": 95,
        "offline": false,
        "marked": false,
        "lastCheck": null,
        "tags": [],
        "clips": [],
        "disabledClips": [],
        "blacklist": [],
        "count": 0,
        "countComplete": false,
        "dirOfSources": false,
        "includeRetweets": false,
        "includeReplies": false,
        "url": "http://profmes.link:45869/get_files/search_files?tags=[\"bimbo\", \"-exu\"]",
        "duration": null,
        "resolution": null
      },
      {
        "id": 96,
        "offline": false,
        "marked": false,
        "lastCheck": null,
        "tags": [],
        "clips": [],
        "disabledClips": [],
        "blacklist": [],
        "count": 0,
        "countComplete": false,
        "dirOfSources": false,
        "includeRetweets": false,
        "includeReplies": false,
        "url": "http://profmes.link:45869/get_files/search_files?tags=[\"blank\", \"-exu\"]",
        "duration": null,
        "resolution": null
      },
      {
        "id": 97,
        "offline": false,
        "marked": false,
        "lastCheck": null,
        "tags": [],
        "clips": [],
        "disabledClips": [],
        "blacklist": [],
        "count": 0,
        "countComplete": false,
        "dirOfSources": false,
        "includeRetweets": false,
        "includeReplies": false,
        "url": "http://profmes.link:45869/get_files/search_files?tags=[\"brainwashed\", \"-exu\"]",
        "duration": null,
        "resolution": null
      },
      {
        "id": 98,
        "offline": false,
        "marked": false,
        "lastCheck": null,
        "tags": [],
        "clips": [],
        "disabledClips": [],
        "blacklist": [],
        "count": 0,
        "countComplete": false,
        "dirOfSources": false,
        "includeRetweets": false,
        "includeReplies": false,
        "url": "http://profmes.link:45869/get_files/search_files?tags=[\"brainwashing\", \"-exu\"]",
        "duration": null,
        "resolution": null
      },
      {
        "id": 99,
        "offline": false,
        "marked": false,
        "lastCheck": null,
        "tags": [],
        "clips": [],
        "disabledClips": [],
        "blacklist": [],
        "count": 0,
        "countComplete": false,
        "dirOfSources": false,
        "includeRetweets": false,
        "includeReplies": false,
        "url": "http://profmes.link:45869/get_files/search_files?tags=[\"cockslut\", \"-exu\"]",
        "duration": null,
        "resolution": null
      },
      {
        "id": 100,
        "offline": false,
        "marked": false,
        "lastCheck": null,
        "tags": [],
        "clips": [],
        "disabledClips": [],
        "blacklist": [],
        "count": 0,
        "countComplete": false,
        "dirOfSources": false,
        "includeRetweets": false,
        "includeReplies": false,
        "url": "http://profmes.link:45869/get_files/search_files?tags=[\"cumslut\", \"-exu\"]",
        "duration": null,
        "resolution": null
      },
      {
        "id": 101,
        "offline": false,
        "marked": false,
        "lastCheck": null,
        "tags": [],
        "clips": [],
        "disabledClips": [],
        "blacklist": [],
        "count": 0,
        "countComplete": false,
        "dirOfSources": false,
        "includeRetweets": false,
        "includeReplies": false,
        "url": "http://profmes.link:45869/get_files/search_files?tags=[\"doll\", \"-exu\"]",
        "duration": null,
        "resolution": null
      },
      {
        "id": 102,
        "offline": false,
        "marked": false,
        "lastCheck": null,
        "tags": [],
        "clips": [],
        "disabledClips": [],
        "blacklist": [],
        "count": 0,
        "countComplete": false,
        "dirOfSources": false,
        "includeRetweets": false,
        "includeReplies": false,
        "url": "http://profmes.link:45869/get_files/search_files?tags=[\"drooling\", \"-exu\"]",
        "duration": null,
        "resolution": null
      },
      {
        "id": 103,
        "offline": false,
        "marked": false,
        "lastCheck": null,
        "tags": [],
        "clips": [],
        "disabledClips": [],
        "blacklist": [],
        "count": 0,
        "countComplete": false,
        "dirOfSources": false,
        "includeRetweets": false,
        "includeReplies": false,
        "url": "http://profmes.link:45869/get_files/search_files?tags=[\"edging\", \"-exu\"]",
        "duration": null,
        "resolution": null
      },
      {
        "id": 104,
        "offline": false,
        "marked": false,
        "lastCheck": null,
        "tags": [],
        "clips": [],
        "disabledClips": [],
        "blacklist": [],
        "count": 0,
        "countComplete": false,
        "dirOfSources": false,
        "includeRetweets": false,
        "includeReplies": false,
        "url": "http://profmes.link:45869/get_files/search_files?tags=[\"exhibition\", \"-exu\"]",
        "duration": null,
        "resolution": null
      },
      {
        "id": 105,
        "offline": false,
        "marked": false,
        "lastCheck": null,
        "tags": [],
        "clips": [],
        "disabledClips": [],
        "blacklist": [],
        "count": 0,
        "countComplete": false,
        "dirOfSources": false,
        "includeRetweets": false,
        "includeReplies": false,
        "url": "http://profmes.link:45869/get_files/search_files?tags=[\"fuckdoll\", \"-exu\"]",
        "duration": null,
        "resolution": null
      },
      {
        "id": 106,
        "offline": false,
        "marked": false,
        "lastCheck": null,
        "tags": [],
        "clips": [],
        "disabledClips": [],
        "blacklist": [],
        "count": 0,
        "countComplete": false,
        "dirOfSources": false,
        "includeRetweets": false,
        "includeReplies": false,
        "url": "http://profmes.link:45869/get_files/search_files?tags=[\"good girl\", \"-exu\"]",
        "duration": null,
        "resolution": null
      },
      {
        "id": 107,
        "offline": false,
        "marked": false,
        "lastCheck": null,
        "tags": [],
        "clips": [],
        "disabledClips": [],
        "blacklist": [],
        "count": 0,
        "countComplete": false,
        "dirOfSources": false,
        "includeRetweets": false,
        "includeReplies": false,
        "url": "http://profmes.link:45869/get_files/search_files?tags=[\"hypnokink\", \"-exu\"]",
        "duration": null,
        "resolution": null
      },
      {
        "id": 108,
        "offline": false,
        "marked": false,
        "lastCheck": null,
        "tags": [],
        "clips": [],
        "disabledClips": [],
        "blacklist": [],
        "count": 0,
        "countComplete": false,
        "dirOfSources": false,
        "includeRetweets": false,
        "includeReplies": false,
        "url": "http://profmes.link:45869/get_files/search_files?tags=[\"hypnokink\", \"eye fixation\", \"-exu\"]",
        "duration": null,
        "resolution": null
      },
      {
        "id": 109,
        "offline": false,
        "marked": false,
        "lastCheck": null,
        "tags": [],
        "clips": [],
        "disabledClips": [],
        "blacklist": [],
        "count": 0,
        "countComplete": false,
        "dirOfSources": false,
        "includeRetweets": false,
        "includeReplies": false,
        "url": "http://profmes.link:45869/get_files/search_files?tags=[\"mantra\", \"-exu\"]",
        "duration": null,
        "resolution": null
      },
      {
        "id": 110,
        "offline": false,
        "marked": false,
        "lastCheck": null,
        "tags": [],
        "clips": [],
        "disabledClips": [],
        "blacklist": [],
        "count": 0,
        "countComplete": false,
        "dirOfSources": false,
        "includeRetweets": false,
        "includeReplies": false,
        "url": "http://profmes.link:45869/get_files/search_files?tags=[\"mesmerizing\", \"-exu\"]",
        "duration": null,
        "resolution": null
      },
      {
        "id": 111,
        "offline": false,
        "marked": false,
        "lastCheck": null,
        "tags": [],
        "clips": [],
        "disabledClips": [],
        "blacklist": [],
        "count": 0,
        "countComplete": false,
        "dirOfSources": false,
        "includeRetweets": false,
        "includeReplies": false,
        "url": "http://profmes.link:45869/get_files/search_files?tags=[\"mesmerizing\", \"no text\", \"-exu\"]",
        "duration": null,
        "resolution": null
      },
      {
        "id": 112,
        "offline": false,
        "marked": false,
        "lastCheck": null,
        "tags": [],
        "clips": [],
        "disabledClips": [],
        "blacklist": [],
        "count": 0,
        "countComplete": false,
        "dirOfSources": false,
        "includeRetweets": false,
        "includeReplies": false,
        "url": "http://profmes.link:45869/get_files/search_files?tags=[\"mindfuck\", \"-exu\"]",
        "duration": null,
        "resolution": null
      },
      {
        "id": 113,
        "offline": false,
        "marked": false,
        "lastCheck": null,
        "tags": [],
        "clips": [],
        "disabledClips": [],
        "blacklist": [],
        "count": 0,
        "countComplete": false,
        "dirOfSources": false,
        "includeRetweets": false,
        "includeReplies": false,
        "url": "http://profmes.link:45869/get_files/search_files?tags=[\"mindfucked\", \"-exu\"]",
        "duration": null,
        "resolution": null
      },
      {
        "id": 114,
        "offline": false,
        "marked": false,
        "lastCheck": null,
        "tags": [],
        "clips": [],
        "disabledClips": [],
        "blacklist": [],
        "count": 0,
        "countComplete": false,
        "dirOfSources": false,
        "includeRetweets": false,
        "includeReplies": false,
        "url": "http://profmes.link:45869/get_files/search_files?tags=[\"obey\", \"-exu\"]",
        "duration": null,
        "resolution": null
      },
      {
        "id": 115,
        "offline": false,
        "marked": false,
        "lastCheck": null,
        "tags": [],
        "clips": [],
        "disabledClips": [],
        "blacklist": [],
        "count": 0,
        "countComplete": false,
        "dirOfSources": false,
        "includeRetweets": false,
        "includeReplies": false,
        "url": "http://profmes.link:45869/get_files/search_files?tags=[\"obey\", \"pleasure, \"-exu\"]",
        "duration": null,
        "resolution": null
      },
      {
        "id": 116,
        "offline": false,
        "marked": false,
        "lastCheck": null,
        "tags": [],
        "clips": [],
        "disabledClips": [],
        "blacklist": [],
        "count": 0,
        "countComplete": false,
        "dirOfSources": false,
        "includeRetweets": false,
        "includeReplies": false,
        "url": "http://profmes.link:45869/get_files/search_files?tags=[\"pleasure\", \"-exu\"]",
        "duration": null,
        "resolution": null
      },
      {
        "id": 117,
        "offline": false,
        "marked": false,
        "lastCheck": null,
        "tags": [],
        "clips": [],
        "disabledClips": [],
        "blacklist": [],
        "count": 0,
        "countComplete": false,
        "dirOfSources": false,
        "includeRetweets": false,
        "includeReplies": false,
        "url": "http://profmes.link:45869/get_files/search_files?tags=[\"serial recruitment\", \"-exu\"]",
        "duration": null,
        "resolution": null
      },
      {
        "id": 118,
        "offline": false,
        "marked": false,
        "lastCheck": null,
        "tags": [],
        "clips": [],
        "disabledClips": [],
        "blacklist": [],
        "count": 0,
        "countComplete": false,
        "dirOfSources": false,
        "includeRetweets": false,
        "includeReplies": false,
        "url": "http://profmes.link:45869/get_files/search_files?tags=[\"slut\", \"-exu\"]",
        "duration": null,
        "resolution": null
      },
      {
        "id": 119,
        "offline": false,
        "marked": false,
        "lastCheck": null,
        "tags": [],
        "clips": [],
        "disabledClips": [],
        "blacklist": [],
        "count": 0,
        "countComplete": false,
        "dirOfSources": false,
        "includeRetweets": false,
        "includeReplies": false,
        "url": "http://profmes.link:45869/get_files/search_files?tags=[\"submit\", \"-exu\"]",
        "duration": null,
        "resolution": null
      },
      {
        "id": 120,
        "offline": false,
        "marked": false,
        "lastCheck": null,
        "tags": [],
        "clips": [],
        "disabledClips": [],
        "blacklist": [],
        "count": 0,
        "countComplete": false,
        "dirOfSources": false,
        "includeRetweets": false,
        "includeReplies": false,
        "url": "http://profmes.link:45869/get_files/search_files?tags=[\"zapnosis\", \"-exu\"]",
        "duration": null,
        "resolution": null
      }
    ],
    "timingFunction": "tf.sin",
    "timingConstant": 1000,
    "timingMin": 2000,
    "timingMax": 8000,
    "timingSinRate": 100,
    "timingBPMMulti": 10,
    "backForth": false,
    "backForthTF": "tf.c",
    "backForthConstant": 1000,
    "backForthMin": 200,
    "backForthMax": 1200,
    "backForthSinRate": 100,
    "backForthBPMMulti": 10,
    "imageType": "it.fitBestNoClip",
    "backgroundType": "bt.blur",
    "backgroundColor": "#000000",
    "backgroundColorSet": [],
    "backgroundBlur": 8,
    "imageTypeFilter": "if.images",
    "fullSource": false,
    "imageOrientation": "ot.original",
    "gifOption": "go.full",
    "gifTimingConstant": 3000,
    "gifTimingMin": 1000,
    "gifTimingMax": 3000,
    "videoOrientation": "ot.original",
    "videoOption": "vo.none",
    "videoTimingConstant": 3000,
    "videoTimingMin": 1000,
    "videoTimingMax": 3000,
    "videoSpeed": 10,
    "videoRandomSpeed": false,
    "videoSpeedMin": 5,
    "videoSpeedMax": 20,
    "randomVideoStart": false,
    "continueVideo": false,
    "playVideoClips": true,
    "skipVideoStart": 0,
    "skipVideoEnd": 0,
    "videoVolume": 0,
    "weightFunction": "wf.i",
    "sourceOrderFunction": "sof.random",
    "forceAllSource": false,
    "orderFunction": "of.random",
    "forceAll": true,
    "zoom": true,
    "zoomRandom": true,
    "zoomStart": 1,
    "zoomStartMin": 0.3,
    "zoomStartMax": 0.8,
    "zoomEnd": 2,
    "zoomEndMin": 1,
    "zoomEndMax": 1.2,
    "horizTransType": "htf.none",
    "horizTransLevel": 10,
    "horizTransLevelMin": 5,
    "horizTransLevelMax": 10,
    "horizTransRandom": false,
    "vertTransType": "vtf.none",
    "vertTransLevel": 10,
    "vertTransLevelMin": 5,
    "vertTransLevelMax": 10,
    "vertTransRandom": false,
    "transTF": "tf.scene",
    "transDuration": 5000,
    "transDurationMin": 1000,
    "transDurationMax": 7000,
    "transSinRate": 100,
    "transBPMMulti": 10,
    "transEase": "ea.linear",
    "transExp": 6,
    "transAmp": 20,
    "transPer": 6,
    "transOv": 3,
    "crossFade": true,
    "crossFadeAudio": false,
    "fadeTF": "tf.scene",
    "fadeDuration": 500,
    "fadeDurationMin": 100,
    "fadeDurationMax": 700,
    "fadeSinRate": 100,
    "fadeBPMMulti": 10,
    "fadeEase": "ea.linear",
    "fadeExp": 6,
    "fadeAmp": 20,
    "fadePer": 6,
    "fadeOv": 3,
    "slide": false,
    "slideTF": "tf.c",
    "slideType": "stf.left",
    "slideDistance": 100,
    "slideDuration": 500,
    "slideDurationMin": 100,
    "slideDurationMax": 700,
    "slideSinRate": 100,
    "slideBPMMulti": 10,
    "slideEase": "ea.linear",
    "slideExp": 6,
    "slideAmp": 20,
    "slidePer": 6,
    "slideOv": 3,
    "strobe": true,
    "strobePulse": false,
    "strobeLayer": "sl.top",
    "strobeOpacity": 1,
    "strobeTF": "tf.c",
    "strobeTime": 100,
    "strobeTimeMin": 100,
    "strobeTimeMax": 300,
    "strobeSinRate": 100,
    "strobeBPMMulti": 10,
    "strobeDelayTF": "tf.c",
    "strobeDelay": 200,
    "strobeDelayMin": 100,
    "strobeDelayMax": 300,
    "strobeDelaySinRate": 100,
    "strobeDelayBPMMulti": 10,
    "strobeColorType": "bt.color",
    "strobeColor": "#FFFFFF",
    "strobeColorSet": [],
    "strobeEase": "ea.linear",
    "strobeExp": 6,
    "strobeAmp": 20,
    "strobePer": 6,
    "strobeOv": 3,
    "fadeInOut": false,
    "fadeIOPulse": false,
    "fadeIOTF": "tf.scene",
    "fadeIODuration": 2000,
    "fadeIODurationMin": 2000,
    "fadeIODurationMax": 5000,
    "fadeIOSinRate": 100,
    "fadeIOBPMMulti": 10,
    "fadeIODelayTF": "tf.c",
    "fadeIODelay": 2000,
    "fadeIODelayMin": 2000,
    "fadeIODelayMax": 5000,
    "fadeIODelaySinRate": 100,
    "fadeIODelayBPMMulti": 10,
    "fadeIOStartEase": "ea.linear",
    "fadeIOStartExp": 6,
    "fadeIOStartAmp": 20,
    "fadeIOStartPer": 6,
    "fadeIOStartOv": 3,
    "fadeIOEndEase": "ea.linear",
    "fadeIOEndExp": 6,
    "fadeIOEndAmp": 20,
    "fadeIOEndPer": 6,
    "fadeIOEndOv": 3,
    "panning": false,
    "panTF": "tf.c",
    "panDuration": 2000,
    "panDurationMin": 2000,
    "panDurationMax": 5000,
    "panSinRate": 100,
    "panBPMMulti": 10,
    "panHorizTransType": "htf.none",
    "panHorizTransImg": false,
    "panHorizTransLevel": 10,
    "panHorizTransLevelMax": 10,
    "panHorizTransLevelMin": 5,
    "panHorizTransRandom": false,
    "panVertTransType": "vtf.none",
    "panVertTransImg": false,
    "panVertTransLevel": 10,
    "panVertTransLevelMax": 10,
    "panVertTransLevelMin": 5,
    "panVertTransRandom": false,
    "panStartEase": "ea.linear",
    "panStartExp": 6,
    "panStartAmp": 20,
    "panStartPer": 6,
    "panStartOv": 3,
    "panEndEase": "ea.linear",
    "panEndExp": 6,
    "panEndAmp": 20,
    "panEndPer": 6,
    "panEndOv": 3,
    "gridScene": false,
    "scriptScene": false,
    "generatorMax": 100,
    "overlayEnabled": true,
    "overlays": [],
    "nextSceneID": 0,
    "nextSceneTime": 900,
    "nextSceneAllImages": false,
    "persistAudio": false,
    "persistText": false,
    "nextSceneRandomID": 0,
    "nextSceneRandoms": [],
    "libraryID": -1,
    "audioScene": false,
    "audioEnabled": true,
    "audioPlaylists": [],
    "audioStartIndex": 0,
    "textEnabled": true,
    "scriptPlaylists": [
      {
        "scripts": [
          {
            "id": 17,
            "marked": false,
            "tags": [],
            "stopAtEnd": false,
            "nextSceneAtEnd": false,
            "syncWithAudio": true,
            "blink": {
              "color": "#FFFFFF",
              "fontSize": 20,
              "fontFamily": "Arial Black,Arial Bold,Gadget,sans-serif",
              "border": false,
              "borderpx": 5,
              "borderColor": "#000000"
            },
            "caption": {
              "color": "#FFFFFF",
              "fontSize": 8,
              "fontFamily": "Helvetica Neue,Helvetica,Arial,sans-serif",
              "border": false,
              "borderpx": 3,
              "borderColor": "#000000"
            },
            "captionBig": {
              "color": "#FFFFFF",
              "fontSize": 12,
              "fontFamily": "Arial Black,Arial Bold,Gadget,sans-serif",
              "border": false,
              "borderpx": 4,
              "borderColor": "#000000"
            },
            "count": {
              "color": "#FFFFFF",
              "fontSize": 20,
              "fontFamily": "Arial Black,Arial Bold,Gadget,sans-serif",
              "border": false,
              "borderpx": 5,
              "borderColor": "#000000"
            },
            "url": "file:///Users/seamusreynolds/Sync/PillowTalkFullEdition/FlipFlipScenes/caption%20scripts/kate_is_a_fuckdoll.txt",
            "opacity": 100
          }
        ],
        "shuffle": false,
        "repeat": "rp.all"
      }
    ],
    "scriptStartIndex": 0,
    "regenerate": true,
    "generatorWeights": null,
    "openTab": 3,
    "rotatePortrait": false,
    "textSource": null,
    "textEndStop": null,
    "textNextScene": null,
    "blinkColor": null,
    "blinkFontSize": null,
    "blinkFontFamily": null,
    "blinkBorder": null,
    "blinkBorderpx": null,
    "blinkBorderColor": null,
    "captionColor": null,
    "captionFontSize": null,
    "captionFontFamily": null,
    "captionBorder": null,
    "captionBorderpx": null,
    "captionBorderColor": null,
    "captionBigColor": null,
    "captionBigFontSize": null,
    "captionBigFontFamily": null,
    "captionBigBorder": null,
    "captionBigBorderpx": null,
    "captionBigBorderColor": null,
    "countColor": null,
    "countFontSize": null,
    "countFontFamily": null,
    "countBorder": null,
    "countBorderpx": null,
    "countBorderColor": null,
    "effectLevel": 0,
    "textKind": "",
    "audioURL": "",
    "overlaySceneID": 0,
    "overlaySceneOpacity": 0.5,
    "transFull": false,
    "fadeFull": false,
    "playFullGif": false,
    "playFullVideo": false,
    "gridView": false,
    "grid": null,
    "audios": null
  }
]